{
  "cars": [
    {
      "id": 1,
      "number": "MZC 2345",
      "date": "2022-1-17T17:30:31.098Z",
      "stateID": 5,
      "worker": 3
    },
    {
      "id": 2,
      "number": "XZQ 2847",
      "date": "2022-1-17T18:39:34.091Z",
      "stateID": 3,
      "worker": 2
    },
    {
      "id": 3,
      "number": "LKW 0987",
      "date": "2022-1-17T19:20:14.298Z",
      "stateID": 5,
      "worker": 1
    },
    {
      "number": "kln 5678",
      "date": "2022-08-23T11:59:39.680Z",
      "stateID": 2,
      "worker": "2",
      "id": 4
    },
    {
      "number": "yukj789",
      "date": "2022-08-23T12:01:50.536Z",
      "stateID": 3,
      "worker": "",
      "id": 5
    },
    {
      "number": "sdfghj",
      "date": "2022-08-23T12:17:15.491Z",
      "stateID": 1,
      "worker": "2",
      "id": 6
    },
    {
      "number": "dfghj",
      "date": "2022-08-23T12:19:30.360Z",
      "stateID": 1,
      "worker": "2",
      "id": 7
    },
    {
      "number": "gjhj456",
      "date": "2022-09-28T09:01:38.737Z",
      "stateID": 1,
      "worker": "2",
      "id": 8
    },
    {
      "number": "NYT777",
      "date": "2022-09-28T09:02:39.179Z",
      "stateID": 1,
      "worker": "1",
      "id": 9
    },
    {
      "number": "KYLLA234",
      "date": "2022-09-28T09:04:06.080Z",
      "stateID": 1,
      "worker": "3",
      "id": 10
    },
    {
      "number": "we234",
      "date": "2022-09-28T09:07:34.083Z",
      "stateID": 1,
      "worker": "2",
      "id": 11
    }
  ],
  "states": [
    {
      "id": 1,
      "state": "accepted"
    },
    {
      "id": 2,
      "state": "in progress"
    },
    {
      "id": 3,
      "state": "on hold"
    },
    {
      "id": 4,
      "state": "carwash"
    },
    {
      "id": 5,
      "state": "done"
    }
  ],
  "workers": [
    {
      "id": 1,
      "name": "Tom"
    },
    {
      "id": 2,
      "name": "Timo"
    },
    {
      "id": 3,
      "name": "Jussi"
    }
  ]
}